owotrans
